{
	"name": "LookupTransformation",
	"properties": {
		"type": "MappingDataFlow",
		"typeProperties": {
			"sources": [
				{
					"dataset": {
						"referenceName": "empDataSet",
						"type": "DatasetReference"
					},
					"name": "empsourceASprimarystream"
				},
				{
					"dataset": {
						"referenceName": "depDataSet",
						"type": "DatasetReference"
					},
					"name": "depsourceASlookupstream"
				}
			],
			"sinks": [
				{
					"dataset": {
						"referenceName": "outputDataSet",
						"type": "DatasetReference"
					},
					"name": "sink1"
				}
			],
			"transformations": [
				{
					"name": "lookup1"
				}
			],
			"scriptLines": [
				"source(output(",
				"          EmpId as string,",
				"          Name as string,",
				"          Department as string,",
				"          Country as string",
				"     ),",
				"     allowSchemaDrift: true,",
				"     validateSchema: false,",
				"     ignoreNoFilesFound: false) ~> empsourceASprimarystream",
				"source(output(",
				"          DepId as string,",
				"          DepartmentName as string",
				"     ),",
				"     allowSchemaDrift: true,",
				"     validateSchema: false,",
				"     ignoreNoFilesFound: false) ~> depsourceASlookupstream",
				"empsourceASprimarystream, depsourceASlookupstream lookup(Department == DepId,",
				"     multiple: false,",
				"     pickup: 'any',",
				"     broadcast: 'auto')~> lookup1",
				"lookup1 sink(allowSchemaDrift: true,",
				"     validateSchema: false,",
				"     partitionFileNames:['lookupFile.csv'],",
				"     skipDuplicateMapInputs: true,",
				"     skipDuplicateMapOutputs: true,",
				"     partitionBy('hash', 1)) ~> sink1"
			]
		}
	}
}